{"expireTime":9007200844305096000,"key":"create-remote-file-node-https://dl.airtable.com/.attachments/547c9cdeacc72c52835802a4ee5191af/8376e50f/odtwne4ngxzaknfsel9u.png","val":{"content-type":"image/png","content-length":"12070","connection":"close","x-amz-replication-status":"COMPLETED","last-modified":"Thu, 09 Apr 2020 16:33:27 GMT","x-amz-server-side-encryption":"AES256","x-amz-version-id":"4aJa23pqxnO4kp6jLCTPOKR7CqI4GBkn","accept-ranges":"bytes","server":"AmazonS3","content-security-policy":"default-src 'none'; style-src 'unsafe-inline'; img-src https://*/favicon.ico; sandbox","access-control-allow-origin":"*","x-robots-tag":"none","x-xss-protection":"1; mode=block","x-content-type-options":"nosniff","referrer-policy":"no-referrer","date":"Fri, 15 May 2020 17:35:05 GMT","etag":"\"8353c98505d8374422edc84b61bfde46\"","x-cache":"RefreshHit from cloudfront","via":"1.1 e09ee53f26574d3b79d9e57c14a34ea4.cloudfront.net (CloudFront)","x-amz-cf-pop":"LHR61-C1","x-amz-cf-id":"SpFCQmC_X08XFlFYFW8ozO0iduQzvwOtr51BYlvC6UtyZxJF5UUlYw=="}}