{"expireTime":9007200844305171000,"key":"create-remote-file-node-https://dl.airtable.com/.attachments/e1a43fab4ef69613ace2ac9818fca8df/3f9f3f17/priscilla-du-preez-YshiKS99FjM-unsplash.jpg","val":{"content-type":"image/jpeg","content-length":"1117426","connection":"close","x-amz-replication-status":"COMPLETED","last-modified":"Thu, 07 May 2020 20:05:32 GMT","x-amz-server-side-encryption":"AES256","x-amz-version-id":"zZ9l9ERo.eoWLOhl8xDwSmfALMPKQFT8","accept-ranges":"bytes","server":"AmazonS3","content-security-policy":"default-src 'none'; style-src 'unsafe-inline'; img-src https://*/favicon.ico; sandbox","access-control-allow-origin":"*","x-robots-tag":"none","x-xss-protection":"1; mode=block","x-content-type-options":"nosniff","referrer-policy":"no-referrer","date":"Fri, 15 May 2020 17:36:20 GMT","etag":"\"78d520d36661081e871d7da3f3728913\"","x-cache":"RefreshHit from cloudfront","via":"1.1 46d5c1a4d1e3a5c8a14bdb9b6676ba11.cloudfront.net (CloudFront)","x-amz-cf-pop":"LHR61-C1","x-amz-cf-id":"liAQ1X63AqzIL5AegiB_iaaDhPbiYKGWjiqcuEmJ0ECMvuU2_m33Og=="}}