{"expireTime":9007200844305265000,"key":"create-remote-file-node-https://dl.airtable.com/.attachments/60931b711ab1fe007ffc5e4df89ea957/15963e5a/www.evercomm.com.sg-5.jpeg","val":{"content-type":"image/jpeg","content-length":"11101","connection":"close","x-amz-replication-status":"COMPLETED","last-modified":"Sat, 29 Feb 2020 01:08:17 GMT","x-amz-server-side-encryption":"AES256","x-amz-version-id":"6eeGni1hD1PBvw2Q49YQ9b0u_OsQf_aR","accept-ranges":"bytes","server":"AmazonS3","content-security-policy":"default-src 'none'; style-src 'unsafe-inline'; img-src https://*/favicon.ico; sandbox","access-control-allow-origin":"*","x-robots-tag":"none","x-xss-protection":"1; mode=block","x-content-type-options":"nosniff","referrer-policy":"no-referrer","date":"Fri, 15 May 2020 17:37:54 GMT","etag":"\"b619bd0b6328c9714e984eae32b4eb5f\"","x-cache":"RefreshHit from cloudfront","via":"1.1 c334b6410f9d489eb2a951a4371f3d18.cloudfront.net (CloudFront)","x-amz-cf-pop":"LHR61-C1","x-amz-cf-id":"fLY-A2-49Fs6OX9cASYy_-KnatvqHcuoVwJIkMHvQ7QNY6h3RfHAgQ=="}}