{"expireTime":9007200844305220000,"key":"create-remote-file-node-https://dl.airtable.com/.attachments/ea59b59d3862b96302ac419eaf461412/4c93c188/sunfolding.com-2.jpeg","val":{"content-type":"image/jpeg","content-length":"34929","connection":"close","x-amz-replication-status":"COMPLETED","last-modified":"Sat, 29 Feb 2020 01:13:31 GMT","x-amz-server-side-encryption":"AES256","x-amz-version-id":"YJx_qx81RWfl62c0AXnD0j7JOjSMiXng","accept-ranges":"bytes","server":"AmazonS3","content-security-policy":"default-src 'none'; style-src 'unsafe-inline'; img-src https://*/favicon.ico; sandbox","access-control-allow-origin":"*","x-robots-tag":"none","x-xss-protection":"1; mode=block","x-content-type-options":"nosniff","referrer-policy":"no-referrer","date":"Fri, 15 May 2020 17:37:09 GMT","etag":"\"15ba23bf0b914425e96545e0595ac962\"","x-cache":"RefreshHit from cloudfront","via":"1.1 e3572bc2867545c7e2bf0953e1795991.cloudfront.net (CloudFront)","x-amz-cf-pop":"LHR61-C1","x-amz-cf-id":"E6WzfmrLD2sC9ndVnSutv1UdkEdWEAzVzTkSWt6PSOt_pGv-GdDLGw=="}}