{"expireTime":9007200843167180000,"key":"create-remote-file-node-https://dl.airtable.com/.attachments/1002f3329c0d0080ad312a50dada2ffb/774d683d/www.marinatex.co.uk-5.jpeg","val":{"content-type":"image/jpeg","content-length":"23862","connection":"close","date":"Sat, 02 May 2020 13:14:40 GMT","x-amz-replication-status":"COMPLETED","last-modified":"Sat, 29 Feb 2020 01:10:40 GMT","etag":"\"eec8ea4a11ab1c9bf634cd30dbdd7fa1\"","x-amz-server-side-encryption":"AES256","x-amz-version-id":"grl_BylcpGhHTm2dEcIwBWPtICgvzMeX","accept-ranges":"bytes","server":"AmazonS3","content-security-policy":"default-src 'none'; style-src 'unsafe-inline'; img-src https://*/favicon.ico; sandbox","access-control-allow-origin":"*","x-robots-tag":"none","x-xss-protection":"1; mode=block","x-content-type-options":"nosniff","referrer-policy":"no-referrer","x-cache":"Hit from cloudfront","via":"1.1 d1a8cc0bb52400f43698b4c3cd691acd.cloudfront.net (CloudFront)","x-amz-cf-pop":"LHR61-C1","x-amz-cf-id":"Uql4EGPUfGDpIGieDUC7F2qV0Vwo4DxufkNuCCBC9zxmkkcLuwzgJg==","age":"909"}}