{"expireTime":9007200843167130000,"key":"create-remote-file-node-https://dl.airtable.com/.attachments/60b678a0fa4b67f3869cac56d660068a/3950580a/ksegawj6dszwxznor0ie","val":{"content-type":"image/png","content-length":"6572","connection":"close","x-amz-replication-status":"COMPLETED","last-modified":"Mon, 27 Apr 2020 15:27:26 GMT","x-amz-server-side-encryption":"AES256","x-amz-version-id":"OUc..iOEeAHQcjBbdOUtOKDX07ajZQUQ","accept-ranges":"bytes","server":"AmazonS3","content-security-policy":"default-src 'none'; style-src 'unsafe-inline'; img-src https://*/favicon.ico; sandbox","access-control-allow-origin":"*","x-robots-tag":"none","x-xss-protection":"1; mode=block","x-content-type-options":"nosniff","referrer-policy":"no-referrer","date":"Sat, 02 May 2020 13:08:20 GMT","etag":"\"25062ed3cc35b31975c98e98af47e516\"","x-cache":"Hit from cloudfront","via":"1.1 04354ce99e843be4590eff596a34d268.cloudfront.net (CloudFront)","x-amz-cf-pop":"LHR61-C1","x-amz-cf-id":"6JbuibqQRXvT8GZ5IGt3y6SASyIawiUWbsH13SZbC0Q5z1_Kr1dJOA==","age":"1239"}}