{"expireTime":9007200844305163000,"key":"create-remote-file-node-https://dl.airtable.com/.attachments/22ab808aff0900d5d3405a168e1cc3d7/c1a71bd9/yrrs1rkbyngaqwbnhzhx","val":{"content-type":"image/jpeg","content-length":"5417","connection":"close","x-amz-replication-status":"COMPLETED","last-modified":"Mon, 27 Apr 2020 15:22:28 GMT","x-amz-server-side-encryption":"AES256","x-amz-version-id":"7Db3i4vf8Nn8z6nR_75HCZQG03irkUdu","accept-ranges":"bytes","server":"AmazonS3","content-security-policy":"default-src 'none'; style-src 'unsafe-inline'; img-src https://*/favicon.ico; sandbox","access-control-allow-origin":"*","x-robots-tag":"none","x-xss-protection":"1; mode=block","x-content-type-options":"nosniff","referrer-policy":"no-referrer","date":"Fri, 15 May 2020 17:36:12 GMT","etag":"\"d0154bef215e61c29035f81e328a03f2\"","x-cache":"RefreshHit from cloudfront","via":"1.1 750c4cd5855cda8293959637bece163c.cloudfront.net (CloudFront)","x-amz-cf-pop":"LHR61-C1","x-amz-cf-id":"uLvhSBScAP6IdKg5KaSxkr8FpFeN_gJBg7SsFeRiDzW3fg-SODUHUg=="}}