{"expireTime":9007200844305207000,"key":"create-remote-file-node-https://dl.airtable.com/.attachments/6f5258cbe29cf9e65c2487bb9fde15f7/33635309/verra.org-3.jpeg","val":{"content-type":"image/jpeg","content-length":"39415","connection":"close","x-amz-replication-status":"COMPLETED","last-modified":"Sat, 29 Feb 2020 01:14:36 GMT","x-amz-server-side-encryption":"AES256","x-amz-version-id":"KOjxWSQMCN79TTar_u.lxf_WBcD_ySEg","accept-ranges":"bytes","server":"AmazonS3","content-security-policy":"default-src 'none'; style-src 'unsafe-inline'; img-src https://*/favicon.ico; sandbox","access-control-allow-origin":"*","x-robots-tag":"none","x-xss-protection":"1; mode=block","x-content-type-options":"nosniff","referrer-policy":"no-referrer","date":"Fri, 15 May 2020 17:36:56 GMT","etag":"\"f788ce48b5b2649d8a488ceb9a9f1033\"","x-cache":"RefreshHit from cloudfront","via":"1.1 c50e6c45c49371a5ebc690255500593d.cloudfront.net (CloudFront)","x-amz-cf-pop":"LHR61-C1","x-amz-cf-id":"i1ALPIeTkxplTssjLtHARqNtKcR8tx8--dFrL-FUQ7Kp9pIYN7C6Jg=="}}