{"expireTime":9007200844305291000,"key":"create-remote-file-node-https://dl.airtable.com/.attachments/b68d95e2a051e6e35fdb1867f77925e1/77eb1b5d/agricool.jpeg","val":{"content-type":"image/jpeg","content-length":"3866","connection":"close","x-amz-replication-status":"COMPLETED","last-modified":"Fri, 17 Jan 2020 16:22:42 GMT","x-amz-server-side-encryption":"AES256","x-amz-version-id":"vSaCPNEOk8yIwpz8RD7bx3LZibpriLo8","accept-ranges":"bytes","server":"AmazonS3","content-security-policy":"default-src 'none'; style-src 'unsafe-inline'; img-src https://*/favicon.ico; sandbox","access-control-allow-origin":"*","x-robots-tag":"none","x-xss-protection":"1; mode=block","x-content-type-options":"nosniff","referrer-policy":"no-referrer","date":"Fri, 15 May 2020 17:38:21 GMT","etag":"\"8aba06fd02d4fe7dc0c66f58f80cae72\"","x-cache":"RefreshHit from cloudfront","via":"1.1 63dac58fb826a8fc06ff08c0724846f7.cloudfront.net (CloudFront)","x-amz-cf-pop":"LHR61-C1","x-amz-cf-id":"9nSb4UD-XlSxu0zTGdHgA_00Hw2dlBLZkCLByiObS5Mj8Epf-ZN54g=="}}