{"expireTime":9007200843167186000,"key":"create-remote-file-node-https://dl.airtable.com/.attachments/d5384be2662fc294e91455e38b3690a6/71805abf/growup.org.uk-2.jpeg","val":{"content-type":"image/jpeg","content-length":"20322","connection":"close","date":"Sat, 02 May 2020 13:29:55 GMT","x-amz-replication-status":"COMPLETED","last-modified":"Sat, 29 Feb 2020 01:09:06 GMT","etag":"\"8ed0a9142721002ae0bed899f38834d9\"","x-amz-server-side-encryption":"AES256","x-amz-version-id":"4UB0qQQbaioxL1y1JPg8L6VssWfvI1Ae","accept-ranges":"bytes","server":"AmazonS3","content-security-policy":"default-src 'none'; style-src 'unsafe-inline'; img-src https://*/favicon.ico; sandbox","access-control-allow-origin":"*","x-robots-tag":"none","x-xss-protection":"1; mode=block","x-content-type-options":"nosniff","referrer-policy":"no-referrer","x-cache":"Miss from cloudfront","via":"1.1 04354ce99e843be4590eff596a34d268.cloudfront.net (CloudFront)","x-amz-cf-pop":"LHR61-C1","x-amz-cf-id":"XDvKVwtvqEDuap6AUruVN0HdxHEgVdRzC_ad3Pspnzc3shtiOpU0Og=="}}