{"expireTime":9007200843167137000,"key":"create-remote-file-node-https://dl.airtable.com/.attachments/28b71f228590e8fbb0b93da53fdd6c04/1951ef63/b7440047d94067961d54d68f8b1bf4f8.jpg","val":{"content-type":"image/jpeg","content-length":"7850","connection":"close","x-amz-replication-status":"COMPLETED","last-modified":"Thu, 09 Apr 2020 16:25:36 GMT","x-amz-server-side-encryption":"AES256","x-amz-version-id":"_YbhGU3LbRuLC0tVZB19k0m43KqmoGNa","accept-ranges":"bytes","server":"AmazonS3","content-security-policy":"default-src 'none'; style-src 'unsafe-inline'; img-src https://*/favicon.ico; sandbox","access-control-allow-origin":"*","x-robots-tag":"none","x-xss-protection":"1; mode=block","x-content-type-options":"nosniff","referrer-policy":"no-referrer","date":"Sat, 02 May 2020 13:08:56 GMT","etag":"\"6d2236198d30030fc482edae7ffdabbb\"","x-cache":"Hit from cloudfront","via":"1.1 0fe4e9874d2e0d61c17aa980fd6da8ee.cloudfront.net (CloudFront)","x-amz-cf-pop":"LHR61-C1","x-amz-cf-id":"5N-CBgUv7Y0zVn4jbssqhallIdv4VpS9TMNQI6OVGpMhQyZAD-oc8w==","age":"1211"}}