{"expireTime":9007200844305285000,"key":"create-remote-file-node-https://dl.airtable.com/.attachments/a5ca9e81017beab8b66cb3e3fec3d1c3/71757cbd/energy-ventures.baywa-re.com-2.jpeg","val":{"content-type":"image/jpeg","content-length":"266427","connection":"close","x-amz-replication-status":"COMPLETED","last-modified":"Sat, 29 Feb 2020 01:06:11 GMT","x-amz-server-side-encryption":"AES256","x-amz-version-id":"OUV8Pl3jDW.OkahL5b1mvDOSHSyuGs4I","accept-ranges":"bytes","server":"AmazonS3","content-security-policy":"default-src 'none'; style-src 'unsafe-inline'; img-src https://*/favicon.ico; sandbox","access-control-allow-origin":"*","x-robots-tag":"none","x-xss-protection":"1; mode=block","x-content-type-options":"nosniff","referrer-policy":"no-referrer","date":"Fri, 15 May 2020 17:38:14 GMT","etag":"\"d1ff81b91ca2c82af250e86de01f9dc1\"","x-cache":"RefreshHit from cloudfront","via":"1.1 46d5c1a4d1e3a5c8a14bdb9b6676ba11.cloudfront.net (CloudFront)","x-amz-cf-pop":"LHR61-C1","x-amz-cf-id":"rXvqLGos1Uteht4M9RhAlz_lwnBbXLPOQiSiWHCOqrypC28eYvHHYg=="}}