{"expireTime":9007200844305129000,"key":"create-remote-file-node-https://dl.airtable.com/.attachments/ade1dc4cef15133a5058c2540bc7addf/14788d1e/ouxmmnzc5u0qvliftckn","val":{"content-type":"image/jpeg","content-length":"10557","connection":"close","x-amz-replication-status":"COMPLETED","last-modified":"Thu, 09 Apr 2020 16:24:53 GMT","x-amz-server-side-encryption":"AES256","x-amz-version-id":"ox_E4oXr.bhxuxKQvxqI.JymuF3Q_Sxi","accept-ranges":"bytes","server":"AmazonS3","content-security-policy":"default-src 'none'; style-src 'unsafe-inline'; img-src https://*/favicon.ico; sandbox","access-control-allow-origin":"*","x-robots-tag":"none","x-xss-protection":"1; mode=block","x-content-type-options":"nosniff","referrer-policy":"no-referrer","date":"Fri, 15 May 2020 17:35:39 GMT","etag":"\"6f928600e251bb4cade9630219f71647\"","x-cache":"RefreshHit from cloudfront","via":"1.1 51608619c24847980745d41550b7ad55.cloudfront.net (CloudFront)","x-amz-cf-pop":"LHR61-C1","x-amz-cf-id":"c2X74WaYMmTltg1WEbIzLV7AqndaMqvWBJ8LOWtUgrP2bVqLlahTeQ=="}}