{"expireTime":9007200843167148000,"key":"create-remote-file-node-https://dl.airtable.com/.attachments/fc336eb7049d37eff464d12cf8022b47/1000ac76/kpxcgkvxljvq31do8e6f.jpg","val":{"content-type":"image/jpeg","content-length":"9266","connection":"close","x-amz-replication-status":"COMPLETED","last-modified":"Thu, 09 Apr 2020 16:26:52 GMT","x-amz-server-side-encryption":"AES256","x-amz-version-id":"gZzRW92kwZYELDWdZwllNy.UtKKeE0Ph","accept-ranges":"bytes","server":"AmazonS3","content-security-policy":"default-src 'none'; style-src 'unsafe-inline'; img-src https://*/favicon.ico; sandbox","access-control-allow-origin":"*","x-robots-tag":"none","x-xss-protection":"1; mode=block","x-content-type-options":"nosniff","referrer-policy":"no-referrer","date":"Sat, 02 May 2020 13:09:31 GMT","etag":"\"39764f54be0965911d979aeac011ab59\"","x-cache":"Hit from cloudfront","via":"1.1 00280e18dbb2b8d7b3cfa8b0e75bdcdc.cloudfront.net (CloudFront)","x-amz-cf-pop":"LHR61-C1","x-amz-cf-id":"B_oou-JjpSWiqfrcqTGxRME5dOf42DQvQQSrP0sIIANX0hUTPd8sfQ==","age":"1185"}}