{"expireTime":9007200843167151000,"key":"create-remote-file-node-https://dl.airtable.com/.attachments/13ca995115a38ddb2aba4cb747f56856/aeb33cd1/Imagefromwww.linkedin.comon2020-02-03at11.32.32PM.png","val":{"content-type":"image/png","content-length":"13504","connection":"close","date":"Sat, 02 May 2020 13:09:42 GMT","x-amz-replication-status":"COMPLETED","last-modified":"Tue, 04 Feb 2020 07:32:25 GMT","etag":"\"f5e8cd430190908caa4b888b38e0f13f\"","x-amz-server-side-encryption":"AES256","x-amz-version-id":"TusW.7dOwzI1cWHMCrrR57sOISyUgkG3","accept-ranges":"bytes","server":"AmazonS3","content-security-policy":"default-src 'none'; style-src 'unsafe-inline'; img-src https://*/favicon.ico; sandbox","access-control-allow-origin":"*","x-robots-tag":"none","x-xss-protection":"1; mode=block","x-content-type-options":"nosniff","referrer-policy":"no-referrer","x-cache":"Hit from cloudfront","via":"1.1 78c24f12c32901deb1cf3a6ac581e591.cloudfront.net (CloudFront)","x-amz-cf-pop":"LHR61-C1","x-amz-cf-id":"qnAZBQkjRIO8QBIrU124Jwxud-RcfJjNzkwVvacrXZDL7GpbWZ7-_w==","age":"1178"}}