{"expireTime":9007200843167155000,"key":"create-remote-file-node-https://dl.airtable.com/.attachments/3bea6a5d6163bb510d029d68d19a49d1/28621000/Imagefromwww.linkedin.comon2020-02-04at10.55.59AM.png","val":{"content-type":"image/png","content-length":"11362","connection":"close","date":"Sat, 02 May 2020 13:09:58 GMT","x-amz-replication-status":"COMPLETED","last-modified":"Tue, 04 Feb 2020 09:56:07 GMT","etag":"\"1b380f367de381d2753795d2b9d9a759\"","x-amz-server-side-encryption":"AES256","x-amz-version-id":"WyMPISOIbqL7pWqGv3xgUfI0OMrdqrTx","accept-ranges":"bytes","server":"AmazonS3","content-security-policy":"default-src 'none'; style-src 'unsafe-inline'; img-src https://*/favicon.ico; sandbox","access-control-allow-origin":"*","x-robots-tag":"none","x-xss-protection":"1; mode=block","x-content-type-options":"nosniff","referrer-policy":"no-referrer","x-cache":"Hit from cloudfront","via":"1.1 ece983986e74e7e31b6830d8531f6fb9.cloudfront.net (CloudFront)","x-amz-cf-pop":"LHR61-C1","x-amz-cf-id":"NFGBRgVsZ19XcieHToq2x0znj-xbZ98f3EpsVpHF6FhXWVmKgRgCHQ==","age":"1165"}}