{"expireTime":9007200844305266000,"key":"create-remote-file-node-https://dl.airtable.com/.attachments/44434b3f20599b705ff5bf8616e46056/d817439e/eu-koreaclimateaction.png","val":{"content-type":"image/png","content-length":"54191","connection":"close","x-amz-replication-status":"COMPLETED","last-modified":"Tue, 28 Apr 2020 13:48:33 GMT","x-amz-server-side-encryption":"AES256","x-amz-version-id":"FpTnMOg3rtzQHUIYnmUBwE7RE2GZQw1L","accept-ranges":"bytes","server":"AmazonS3","content-security-policy":"default-src 'none'; style-src 'unsafe-inline'; img-src https://*/favicon.ico; sandbox","access-control-allow-origin":"*","x-robots-tag":"none","x-xss-protection":"1; mode=block","x-content-type-options":"nosniff","referrer-policy":"no-referrer","date":"Fri, 15 May 2020 17:37:54 GMT","etag":"\"d4ae6f3096a0ad64407b54691005ee7c\"","x-cache":"RefreshHit from cloudfront","via":"1.1 46d5c1a4d1e3a5c8a14bdb9b6676ba11.cloudfront.net (CloudFront)","x-amz-cf-pop":"LHR61-C1","x-amz-cf-id":"6tGnL4_9HpqCHMbf5GcwsSssE5VJKWywr8Yg6jJc57E0ufJZsYWYIw=="}}