{"expireTime":9007200844305145000,"key":"create-remote-file-node-https://dl.airtable.com/.attachments/1ee2af483b9c84a458807850d3b605c8/2ed33cc1/jwrfkj0z2ionqaiy7a4t.png","val":{"content-type":"image/png","content-length":"5755","connection":"close","x-amz-replication-status":"COMPLETED","last-modified":"Thu, 09 Apr 2020 16:11:51 GMT","x-amz-server-side-encryption":"AES256","x-amz-version-id":"jaEA_.ACqSbqF4alyNh.0XAmRN5jqj8T","accept-ranges":"bytes","server":"AmazonS3","content-security-policy":"default-src 'none'; style-src 'unsafe-inline'; img-src https://*/favicon.ico; sandbox","access-control-allow-origin":"*","x-robots-tag":"none","x-xss-protection":"1; mode=block","x-content-type-options":"nosniff","referrer-policy":"no-referrer","date":"Fri, 15 May 2020 17:35:54 GMT","etag":"\"0dc3209fa8817cb84ddc638e913286f0\"","x-cache":"RefreshHit from cloudfront","via":"1.1 46d5c1a4d1e3a5c8a14bdb9b6676ba11.cloudfront.net (CloudFront)","x-amz-cf-pop":"LHR61-C1","x-amz-cf-id":"gpLnnql33kc4faK-mi4N9Cn4EzwN65tvvC_ulzISXZJH2A5ZJ-j_bA=="}}