{"expireTime":9007200843167161000,"key":"create-remote-file-node-https://dl.airtable.com/.attachments/4c897c97b3f3a5efcb42b7ace75c0da7/49eb4599/wundermobility.com-5.jpeg","val":{"content-type":"image/jpeg","content-length":"67534","connection":"close","date":"Sat, 02 May 2020 13:13:54 GMT","x-amz-replication-status":"COMPLETED","last-modified":"Sat, 29 Feb 2020 01:15:13 GMT","etag":"\"83cb38021378fd68329aa3897154d450\"","x-amz-server-side-encryption":"AES256","x-amz-version-id":"etkD8DnkmTaTMQ0zuc9B5L2OZL33bvnP","accept-ranges":"bytes","server":"AmazonS3","content-security-policy":"default-src 'none'; style-src 'unsafe-inline'; img-src https://*/favicon.ico; sandbox","access-control-allow-origin":"*","x-robots-tag":"none","x-xss-protection":"1; mode=block","x-content-type-options":"nosniff","referrer-policy":"no-referrer","x-cache":"Hit from cloudfront","via":"1.1 04354ce99e843be4590eff596a34d268.cloudfront.net (CloudFront)","x-amz-cf-pop":"LHR61-C1","x-amz-cf-id":"t1_DxosBzjS_3Dpe4E__ZOvORTfZ1Y9DRMst8ZiDYF7rDF7nEcw6gw==","age":"937"}}