{"expireTime":9007200843167130000,"key":"create-remote-file-node-https://dl.airtable.com/.attachments/0c4ddca0d23099c05db83aae83a2f6af/f7138169/aruklzn1uduy1mpnvv4l","val":{"content-type":"image/png","content-length":"6511","connection":"close","x-amz-replication-status":"COMPLETED","last-modified":"Thu, 09 Apr 2020 16:16:02 GMT","x-amz-server-side-encryption":"AES256","x-amz-version-id":"M_RgU1CV9z3s7edk5gM8lYyNzxvhCdAG","accept-ranges":"bytes","server":"AmazonS3","content-security-policy":"default-src 'none'; style-src 'unsafe-inline'; img-src https://*/favicon.ico; sandbox","access-control-allow-origin":"*","x-robots-tag":"none","x-xss-protection":"1; mode=block","x-content-type-options":"nosniff","referrer-policy":"no-referrer","date":"Sat, 02 May 2020 13:08:23 GMT","etag":"\"fc103dd61a534e8f6caec6d0aff41c28\"","x-cache":"Hit from cloudfront","via":"1.1 78c24f12c32901deb1cf3a6ac581e591.cloudfront.net (CloudFront)","x-amz-cf-pop":"LHR61-C1","x-amz-cf-id":"zvYZcq_HYq_NjPVKZXiFXg5E5FlUWP5R0XBSQpt_8WlXks9n3G67YA==","age":"1235"}}