{"expireTime":9007200844305127000,"key":"create-remote-file-node-https://dl.airtable.com/.attachments/30153a20d536cef75d63e9e89ec9d3ca/40f11a3f/495a3f95d07c04db78cd","val":{"content-type":"image/jpeg","content-length":"3981","connection":"close","x-amz-replication-status":"COMPLETED","last-modified":"Thu, 09 Apr 2020 16:19:47 GMT","x-amz-server-side-encryption":"AES256","x-amz-version-id":"sQdeZrG07xfIid3Ky.nnWML3js_Gdv4i","accept-ranges":"bytes","server":"AmazonS3","content-security-policy":"default-src 'none'; style-src 'unsafe-inline'; img-src https://*/favicon.ico; sandbox","access-control-allow-origin":"*","x-robots-tag":"none","x-xss-protection":"1; mode=block","x-content-type-options":"nosniff","referrer-policy":"no-referrer","date":"Fri, 15 May 2020 17:35:37 GMT","etag":"\"0ae8f26f2d6b707049d0929a9b02e6ae\"","x-cache":"RefreshHit from cloudfront","via":"1.1 a10ef2362efd83570036459690ee6d43.cloudfront.net (CloudFront)","x-amz-cf-pop":"LHR61-C1","x-amz-cf-id":"Tj6_k0RylMYxhidUfYet3oTGTrexsAN6Ub7HBB7cJhUgqSr8StzvaQ=="}}