{"expireTime":9007200843167141000,"key":"create-remote-file-node-https://dl.airtable.com/.attachments/144723c1729399d6604fb6b480ffbae2/42c8ff48/qyh006itvmepp86re9kv.jpg","val":{"content-type":"image/jpeg","content-length":"6708","connection":"close","x-amz-replication-status":"COMPLETED","last-modified":"Thu, 09 Apr 2020 16:33:27 GMT","x-amz-server-side-encryption":"AES256","x-amz-version-id":"YWUhgeu3xpuCoLqwf7MY6N6BU41LNjbQ","accept-ranges":"bytes","server":"AmazonS3","content-security-policy":"default-src 'none'; style-src 'unsafe-inline'; img-src https://*/favicon.ico; sandbox","access-control-allow-origin":"*","x-robots-tag":"none","x-xss-protection":"1; mode=block","x-content-type-options":"nosniff","referrer-policy":"no-referrer","date":"Sat, 02 May 2020 13:09:11 GMT","etag":"\"64a4aa772abe85e6e46c34e94ad26b01\"","x-cache":"Hit from cloudfront","via":"1.1 18e6ec21b2a0145722b1ee6278aea970.cloudfront.net (CloudFront)","x-amz-cf-pop":"LHR61-C1","x-amz-cf-id":"mDSliAms8byyXL53NBt6JC0koU04KoxDswPZkHHNoAQeb7nfRxNS-A==","age":"1198"}}