{"expireTime":9007200843167134000,"key":"create-remote-file-node-https://dl.airtable.com/.attachments/5a733624ee069b7a44349c178e15a75d/20b56efa/hqkzxrbytyy8mapretrd","val":{"content-type":"image/jpeg","content-length":"9981","connection":"close","date":"Sat, 02 May 2020 13:08:40 GMT","x-amz-replication-status":"COMPLETED","last-modified":"Thu, 09 Apr 2020 16:22:56 GMT","etag":"\"189e59a4412f554f9762d74f2d9b48cc\"","x-amz-server-side-encryption":"AES256","x-amz-version-id":"o.qIfF_6.pPD4lcDLfEN75xxAkPdLCMH","accept-ranges":"bytes","server":"AmazonS3","content-security-policy":"default-src 'none'; style-src 'unsafe-inline'; img-src https://*/favicon.ico; sandbox","access-control-allow-origin":"*","x-robots-tag":"none","x-xss-protection":"1; mode=block","x-content-type-options":"nosniff","referrer-policy":"no-referrer","x-cache":"Hit from cloudfront","via":"1.1 c334b6410f9d489eb2a951a4371f3d18.cloudfront.net (CloudFront)","x-amz-cf-pop":"LHR61-C1","x-amz-cf-id":"72F3DOXy7uEc2bz0b7Y7uigws8YbCmykTCNWCJKV5-7cPcfUHAzUzw==","age":"1223"}}