{"expireTime":9007200843167136000,"key":"create-remote-file-node-https://dl.airtable.com/.attachments/3f7dcbbed849ff0c18668920e9b7c772/f318b837/oa2owcfol4mqmntwe3j2","val":{"content-type":"image/jpeg","content-length":"8294","connection":"close","x-amz-replication-status":"COMPLETED","last-modified":"Thu, 09 Apr 2020 16:26:36 GMT","x-amz-server-side-encryption":"AES256","x-amz-version-id":"XccpQ5wFWeQhV9S8mQgjqDFfXThxbmDI","accept-ranges":"bytes","server":"AmazonS3","content-security-policy":"default-src 'none'; style-src 'unsafe-inline'; img-src https://*/favicon.ico; sandbox","access-control-allow-origin":"*","x-robots-tag":"none","x-xss-protection":"1; mode=block","x-content-type-options":"nosniff","referrer-policy":"no-referrer","date":"Sat, 02 May 2020 13:08:50 GMT","etag":"\"e71ae692d5899800ac1ac078946f599c\"","x-cache":"Hit from cloudfront","via":"1.1 19a2321144b2039159d43efbb8b9691f.cloudfront.net (CloudFront)","x-amz-cf-pop":"LHR61-C1","x-amz-cf-id":"rVV-fD5C0j7Wp_IkluxigcARNm28gnvXpMZsxSV2z94XPUsV3IBs9Q==","age":"1215"}}