{"expireTime":9007200844305287000,"key":"create-remote-file-node-https://dl.airtable.com/.attachments/586b2dd9cf52a4235984416157dac9b2/f805ef7c/aptechafrica.com-19.jpeg","val":{"content-type":"image/jpeg","content-length":"17300","connection":"close","x-amz-replication-status":"COMPLETED","last-modified":"Sat, 29 Feb 2020 01:15:29 GMT","x-amz-server-side-encryption":"AES256","x-amz-version-id":"lriLBoWxSNzrTndPbLkkxSeGQZA4x7nv","accept-ranges":"bytes","server":"AmazonS3","content-security-policy":"default-src 'none'; style-src 'unsafe-inline'; img-src https://*/favicon.ico; sandbox","access-control-allow-origin":"*","x-robots-tag":"none","x-xss-protection":"1; mode=block","x-content-type-options":"nosniff","referrer-policy":"no-referrer","date":"Fri, 15 May 2020 17:38:17 GMT","etag":"\"3490f9ea7d131e0585c5b5343cfc69d4\"","x-cache":"RefreshHit from cloudfront","via":"1.1 a10ef2362efd83570036459690ee6d43.cloudfront.net (CloudFront)","x-amz-cf-pop":"LHR61-C1","x-amz-cf-id":"hrnlnqnTh1xGkPPHj8s5aJptre2utMecVP-SIinrPgEHmZM0Qatq7A=="}}